pySED/Compressor.py
pySED/FileIO.py
pySED/Lorentz.py
pySED/My_Parsers.py
pySED/Phonon.py
pySED/Plot_SED.py
pySED/__init__.py
pySED/construct_BZ.py
pySED/version.py
pySED/structure/__init__.py
pySED/structure/atoms.py
pySED/structure/generate_data.py
pySED/structure/read_structure.py
scripts/__init__.py
pySED_phonon-1.0.3.dist-info/LICENSE
pySED_phonon-1.0.3.dist-info/METADATA
pySED_phonon-1.0.3.dist-info/WHEEL
pySED_phonon-1.0.3.dist-info/entry_points.txt
pySED_phonon-1.0.3.dist-info/top_level.txt
pySED_phonon-1.0.3.dist-info/RECORD
