Metadata-Version: 2.1
Name: pySED-phonon
Version: 1.0.3
Summary: To implement the SED method in 2010, phonon lifetime can be calculated
Home-page: https://github.com/Tingliangstu/pySED
Author: Liang Ting
Author-email: liangting.zj@gmail.com
License: MIT License
Platform: UNKNOWN
Requires-Python: >=3.7
Requires-Dist: numpy (>=1.15.0)
Requires-Dist: matplotlib (>=3.5.2)
Requires-Dist: seaborn
Requires-Dist: h5py
Requires-Dist: scipy
